hbi/__init__.py
hbi/__main__.py
hbi/buflist.py
hbi/bytesbuf.py
hbi/conn.py
hbi/context.py
hbi/log.py
hbi/me.py
hbi/proto.py
hbi/sendctrl.py
hbi/sockconn.py
hbi/version.py
hbi-1.1.2.dist-info/DESCRIPTION.rst
hbi-1.1.2.dist-info/METADATA
hbi-1.1.2.dist-info/RECORD
hbi-1.1.2.dist-info/WHEEL
hbi-1.1.2.dist-info/metadata.json
hbi-1.1.2.dist-info/top_level.txt
